esnpy/__init__.py
esnpy/esn.py
esnpy/init.py
esnpy/reader.py
esnpy/reservoir.py
esnpy/train.py
esnpy/tune.py
esnpy/type.py
esnpy-0.4.0.dist-info/LICENSE
esnpy-0.4.0.dist-info/METADATA
esnpy-0.4.0.dist-info/WHEEL
esnpy-0.4.0.dist-info/top_level.txt
esnpy-0.4.0.dist-info/RECORD
