Metadata-Version: 2.1
Name: esnpy
Version: 0.4.0
Summary: Out-of-the-box framework for Echo State Networks
Author-email: Théo BL <biasutto.t@gmail.com>
License: The MIT License (MIT)
Project-URL: GitHub, https://github.com/NiziL/esnpy
Keywords: machine learning,neural networks,echo state network
Classifier: Development Status :: 4 - Beta
Classifier: Intended Audience :: Science/Research
Classifier: License :: OSI Approved :: MIT License
Classifier: Operating System :: OS Independent
Classifier: Programming Language :: Python :: 3
Classifier: Topic :: Scientific/Engineering :: Artificial Intelligence
Requires-Python: >=3.9
License-File: LICENSE
Requires-Dist: numpy (>=1.23.0)
Requires-Dist: scipy (>=1.9.3)
Provides-Extra: doc
Requires-Dist: sphinx ; extra == 'doc'
Requires-Dist: sphinx-pyproject ; extra == 'doc'
Provides-Extra: lint
Requires-Dist: black ; extra == 'lint'
Requires-Dist: flake8 ; extra == 'lint'
